pcarpet/__init__.py
pcarpet/pcarpet.py
pcarpet/version.py
pcarpet/tests/__init__.py
pcarpet/tests/test_pcarpet.py
pcarpet-0.2.dist-info/LICENSE
pcarpet-0.2.dist-info/METADATA
pcarpet-0.2.dist-info/WHEEL
pcarpet-0.2.dist-info/top_level.txt
pcarpet-0.2.dist-info/RECORD
