Metadata-Version: 2.1
Name: pcarpet
Version: 0.2
Summary: pcarpet: create a carpet plot from fMRI data and decompose it with PCA.
Home-page: http://github.com/niksirbi/pcarpet
Author: Nikoloz Sirmpilatze
Author-email: niko.sirbiladze@gmail.com
Maintainer: Nikoloz Sirmpilatze
Maintainer-email: niko.sirbiladze@gmail.com
License: MIT
Platform: OS Independent
Classifier: Development Status :: 3 - Alpha
Classifier: Environment :: Console
Classifier: Intended Audience :: Science/Research
Classifier: License :: OSI Approved :: MIT License
Classifier: Operating System :: OS Independent
Classifier: Programming Language :: Python :: 3
Classifier: Topic :: Scientific/Engineering
Requires-Python: >= 3.7
License-File: LICENSE
Requires-Dist: numpy
Requires-Dist: scipy
Requires-Dist: matplotlib
Requires-Dist: pandas
Requires-Dist: scikit-learn
Requires-Dist: nibabel
